{"Date":"2021-02-21T11:20:44.1417383+02:00","Type":"Information","Message":"Application started"}
{"Date":"2021-02-21T11:54:15.2109854+02:00","Type":"Information","Message":"Application started"}
{"Date":"2021-02-21T11:54:56.0812947+02:00","Type":"Information","Message":"Application started"}
{"Date":"2021-02-21T11:56:04.907406+02:00","Type":"Information","Message":"Application started"}
{"Date":"2021-02-21T11:57:17.2588867+02:00","Type":"Information","Message":"Application started"}
{"Date":"2021-02-21T11:57:57.172495+02:00","Type":"Information","Message":"Application started"}
{"Date":"2021-02-21T11:59:08.1902438+02:00","Type":"Information","Message":"Application started"}
{"Date":"2021-02-21T12:03:17.3141616+02:00","Type":"Information","Message":"Application started"}
{"Date":"2021-02-21T12:04:24.793311+02:00","Type":"Information","Message":"Application started"}
{"Date":"2021-02-21T12:17:29.6441471+02:00","Type":"Information","Message":"Application started"}
{"Date":"2021-02-21T12:18:10.5804388+02:00","Type":"Information","Message":"Application started"}
{"Date":"2021-02-21T12:26:18.3654253+02:00","Type":"Information","Message":"Application started"}
{"Date":"2021-02-21T12:26:58.5496851+02:00","Type":"Information","Message":"Application started"}
{"Date":"2021-02-21T12:28:35.4814815+02:00","Type":"Information","Message":"Application started"}
{"Date":"2021-02-21T12:29:49.9926115+02:00","Type":"Information","Message":"Application started"}
{"Date":"2021-02-21T12:53:17.2728218+02:00","Type":"Information","Message":"Application started"}
{"Date":"2021-02-21T12:54:44.6232168+02:00","Type":"Information","Message":"Application started"}
{"Date":"2021-02-21T12:55:12.8989736+02:00","Type":"Information","Message":"Application started"}
{"Date":"2021-02-21T12:55:34.7650589+02:00","Type":"Information","Message":"Application started"}
{"Date":"2021-02-21T12:56:16.0541308+02:00","Type":"Information","Message":"Application started"}
{"Date":"2021-02-21T12:57:23.2771074+02:00","Type":"Information","Message":"Application started"}
{"Date":"2021-02-21T12:58:03.6483924+02:00","Type":"Information","Message":"Application started"}
{"Date":"2021-02-21T13:00:56.8987+02:00","Type":"Information","Message":"Application started"}
{"Date":"2021-02-21T13:04:28.2347177+02:00","Type":"Information","Message":"Application started"}
{"Date":"2021-02-21T13:05:22.5685439+02:00","Type":"Information","Message":"Application started"}
{"Date":"2021-02-21T13:06:30.5465552+02:00","Type":"Information","Message":"Application started"}
{"Date":"2021-02-21T13:06:45.8301954+02:00","Type":"Information","Message":"Application started"}
{"Date":"2021-02-21T13:06:58.9724095+02:00","Type":"Information","Message":"Application started"}
{"Date":"2021-02-21T15:04:36.3264167+02:00","Type":"Information","Message":"Application started"}
{"Date":"2021-02-21T16:00:36.1770991+02:00","Type":"Information","Message":"Application started"}
{"Date":"2021-02-21T16:24:56.9891959+02:00","Type":"Information","Message":"Application started"}
{"Date":"2021-02-21T16:25:48.5061959+02:00","Type":"Information","Message":"Application started"}
